obsidianreadermcp/__init__.py
obsidianreadermcp/__main__.py
obsidianreadermcp/client.py
obsidianreadermcp/config.py
obsidianreadermcp/exceptions.py
obsidianreadermcp/extensions.py
obsidianreadermcp/models.py
obsidianreadermcp/server.py
obsidianreadermcp-0.1.6.dist-info/METADATA
obsidianreadermcp-0.1.6.dist-info/WHEEL
obsidianreadermcp-0.1.6.dist-info/entry_points.txt
obsidianreadermcp-0.1.6.dist-info/licenses/LICENSE
obsidianreadermcp-0.1.6.dist-info/RECORD
