Metadata-Version: 2.4
Name: obsidianreadermcp
Version: 0.1.6
Summary: A comprehensive Python MCP server for managing Obsidian vaults via obsidian-local-rest-api
Project-URL: Homepage, https://github.com/QianJue-CN/ObsidianReaderMCP
Project-URL: Repository, https://github.com/QianJue-CN/ObsidianReaderMCP
Project-URL: Documentation, https://github.com/QianJue-CN/ObsidianReaderMCP/blob/main/README.md
Project-URL: Issues, https://github.com/QianJue-CN/ObsidianReaderMCP/issues
Project-URL: Changelog, https://github.com/QianJue-CN/ObsidianReaderMCP/releases
Author-email: QianJue <QianJue1003@qq.com>
Maintainer-email: QianJue <QianJue1003@qq.com>
License: MIT
License-File: LICENSE
Keywords: ai-assistant,knowledge-management,mcp,model-context-protocol,obsidian
Classifier: Development Status :: 4 - Beta
Classifier: Intended Audience :: Developers
Classifier: License :: OSI Approved :: MIT License
Classifier: Operating System :: OS Independent
Classifier: Programming Language :: Python :: 3
Classifier: Programming Language :: Python :: 3.10
Classifier: Programming Language :: Python :: 3.11
Classifier: Programming Language :: Python :: 3.12
Classifier: Topic :: Office/Business :: Groupware
Classifier: Topic :: Software Development :: Libraries :: Python Modules
Classifier: Topic :: Text Processing :: Markup
Requires-Python: >=3.10
Requires-Dist: httpx>=0.25.0
Requires-Dist: mcp>=1.0.0
Requires-Dist: pydantic>=2.0.0
Requires-Dist: python-dotenv>=1.0.0
Requires-Dist: typing-extensions>=4.0.0
Provides-Extra: dev
Requires-Dist: black>=23.0.0; extra == 'dev'
Requires-Dist: build>=1.0.0; extra == 'dev'
Requires-Dist: flake8>=6.0.0; extra == 'dev'
Requires-Dist: isort>=5.0.0; extra == 'dev'
Requires-Dist: mypy>=1.0.0; extra == 'dev'
Requires-Dist: pytest-asyncio>=0.21.0; extra == 'dev'
Requires-Dist: pytest-cov>=4.0.0; extra == 'dev'
Requires-Dist: pytest>=7.0.0; extra == 'dev'
Requires-Dist: twine>=4.0.0; extra == 'dev'
